openapi_python_embyapi/__init__.py
openapi_python_embyapi/api/__init__.py
openapi_python_embyapi/api/activity_log_service/__init__.py
openapi_python_embyapi/api/activity_log_service/get_system_activitylog_entries.py
openapi_python_embyapi/api/artists_service/__init__.py
openapi_python_embyapi/api/artists_service/get_artists.py
openapi_python_embyapi/api/artists_service/get_artists_albumartists.py
openapi_python_embyapi/api/artists_service/get_artists_by_name.py
openapi_python_embyapi/api/audio_service/__init__.py
openapi_python_embyapi/api/audio_service/get_audio_by_id_stream.py
openapi_python_embyapi/api/audio_service/get_audio_by_id_stream_by_container.py
openapi_python_embyapi/api/audio_service/head_audio_by_id_stream.py
openapi_python_embyapi/api/audio_service/head_audio_by_id_stream_by_container.py
openapi_python_embyapi/api/bif_service/__init__.py
openapi_python_embyapi/api/bif_service/get_items_by_id_thumbnailset.py
openapi_python_embyapi/api/bif_service/get_videos_by_id_index_bif.py
openapi_python_embyapi/api/branding_service/__init__.py
openapi_python_embyapi/api/branding_service/get_branding_configuration.py
openapi_python_embyapi/api/branding_service/get_branding_css.py
openapi_python_embyapi/api/branding_service/get_branding_css_css.py
openapi_python_embyapi/api/channel_service/__init__.py
openapi_python_embyapi/api/channel_service/get_channels.py
openapi_python_embyapi/api/codec_parameter_service/__init__.py
openapi_python_embyapi/api/codec_parameter_service/get_encoding_codecparameters.py
openapi_python_embyapi/api/codec_parameter_service/post_encoding_codecparameters.py
openapi_python_embyapi/api/collection_service/__init__.py
openapi_python_embyapi/api/collection_service/delete_collections_by_id_items.py
openapi_python_embyapi/api/collection_service/post_collections.py
openapi_python_embyapi/api/collection_service/post_collections_by_id_items.py
openapi_python_embyapi/api/collection_service/post_collections_by_id_items_delete.py
openapi_python_embyapi-4.8.0.36.dist-info/METADATA
openapi_python_embyapi-4.8.0.36.dist-info/WHEEL
openapi_python_embyapi-4.8.0.36.dist-info/RECORD
