Metadata-Version: 2.1
Name: openapi-python-embyapi
Version: 4.8.0.36
Summary: A Unofficial Python client library for accessing Emby Server REST API, generated by openapi-python-client
Home-page: https://github.com/Umpire2012/codegen-embyapi/tree/main/openapi-python-embyapi
License: MIT
Author: Umpire2012
Author-email: arno.edwards@outlook.com
Requires-Python: >=3.8,<4.0
Classifier: License :: OSI Approved :: MIT License
Classifier: Programming Language :: Python :: 3
Classifier: Programming Language :: Python :: 3.8
Classifier: Programming Language :: Python :: 3.9
Classifier: Programming Language :: Python :: 3.10
Classifier: Programming Language :: Python :: 3.11
Requires-Dist: attrs (>=21.3.0)
Requires-Dist: httpx (>=0.15.4,<0.25.0)
Requires-Dist: python-dateutil (>=2.8.0,<3.0.0)
Project-URL: Repository, https://github.com/Umpire2012/codegen-embyapi/tree/main/openapi-python-embyapi
